resources/__init__.py
resources/configs/default/README.md
resources/configs/default/agents/claude-style-coder.yml
resources/configs/default/agents/code-reviewer.yml
resources/configs/default/agents/general.yml
resources/configs/default/checkpointers/memory.yml
resources/configs/default/checkpointers/sqlite.yml
resources/configs/default/llms/anthropic.yml
resources/configs/default/llms/bedrock.yml
resources/configs/default/llms/deepseek.yml
resources/configs/default/llms/google.yml
resources/configs/default/llms/lmstudio.yml
resources/configs/default/llms/openai.yml
resources/configs/default/llms/zhipuai.yml
resources/configs/default/prompts/agents/claude-style-coder.md
resources/configs/default/prompts/agents/code-reviewer.md
resources/configs/default/prompts/agents/general.md
resources/configs/default/prompts/prefixes/notes.md
resources/configs/default/prompts/shared/code_compression.md
resources/configs/default/prompts/shared/general_compression.md
resources/configs/default/prompts/subagents/explorer.md
resources/configs/default/prompts/subagents/general-purpose.md
resources/configs/default/prompts/suffixes/environments.md
resources/configs/default/sandboxes/ro-offline-linux.yml
resources/configs/default/sandboxes/ro-offline-macos.yml
resources/configs/default/sandboxes/ro-online-linux.yml
resources/configs/default/sandboxes/ro-online-macos.yml
resources/configs/default/sandboxes/rw-offline-linux.yml
resources/configs/default/sandboxes/rw-offline-macos.yml
resources/configs/default/sandboxes/rw-online-linux.yml
resources/configs/default/sandboxes/rw-online-macos.yml
resources/configs/default/skills/.gitkeep
resources/configs/default/subagents/explorer.yml
resources/configs/default/subagents/general-purpose.yml
resources/features/notes.yml
langrepl/__init__.py
langrepl/agents/__init__.py
langrepl/agents/context.py
langrepl/agents/deep_agent.py
langrepl/agents/factory.py
langrepl/agents/react_agent.py
langrepl/agents/state.py
langrepl/checkpointer/__init__.py
langrepl-1.10.8.dist-info/METADATA
langrepl-1.10.8.dist-info/WHEEL
langrepl-1.10.8.dist-info/entry_points.txt
langrepl-1.10.8.dist-info/licenses/LICENSE
langrepl-1.10.8.dist-info/RECORD
