Metadata-Version: 2.4
Name: langrepl
Version: 1.10.8
Summary: Interactive terminal CLI for building and running LLM agents. Built with LangChain, LangGraph, Prompt Toolkit, and Rich.
Project-URL: Homepage, https://github.com/midodimori/langrepl
Project-URL: Repository, https://github.com/midodimori/langrepl
Project-URL: Issues, https://github.com/midodimori/langrepl/issues
Project-URL: Changelog, https://github.com/midodimori/langrepl/blob/main/CHANGELOG.md
Author-email: midodimori <midodimori@gmail.com>
License: MIT
License-File: LICENSE
Keywords: agent,ai,assistant,chatbot,cli,langchain,langgraph,llm,repl,terminal
Classifier: Development Status :: 4 - Beta
Classifier: Environment :: Console
Classifier: Intended Audience :: Developers
Classifier: License :: OSI Approved :: MIT License
Classifier: Operating System :: MacOS
Classifier: Operating System :: OS Independent
Classifier: Operating System :: POSIX :: Linux
Classifier: Programming Language :: Python :: 3
Classifier: Programming Language :: Python :: 3 :: Only
Classifier: Programming Language :: Python :: 3.13
Classifier: Topic :: Scientific/Engineering :: Artificial Intelligence
Classifier: Topic :: Software Development :: Libraries :: Python Modules
Classifier: Topic :: Terminals
Classifier: Typing :: Typed
Requires-Python: >=3.13
Requires-Dist: aiofiles~=25.1.0
Requires-Dist: aiosqlite~=0.22.1
Requires-Dist: fastapi>=0.128.0
Requires-Dist: greenlet~=3.3.0
Requires-Dist: json-repair~=0.54.3
Requires-Dist: jsonschema~=4.25.1
Requires-Dist: langchain-anthropic~=1.3.0
Requires-Dist: langchain-aws~=1.1.1
Requires-Dist: langchain-community~=0.4.1
Requires-Dist: langchain-core~=1.2.4
Requires-Dist: langchain-deepseek~=1.0.1
Requires-Dist: langchain-google-genai~=4.1.2
Requires-Dist: langchain-mcp-adapters~=0.2.1
Requires-Dist: langchain-ollama~=1.0.1
Requires-Dist: langchain-openai~=1.1.6
Requires-Dist: langchain~=1.2.0
Requires-Dist: langgraph-checkpoint-sqlite~=3.0.1
Requires-Dist: langgraph-cli[inmem]~=0.4.11
Requires-Dist: langgraph-prebuilt~=1.0.5
Requires-Dist: langgraph~=1.0.5
Requires-Dist: markdown-it-py~=4.0.0
Requires-Dist: mdformat~=1.0.0
Requires-Dist: pathspec~=0.12.1
Requires-Dist: prompt-toolkit~=3.0.52
Requires-Dist: pydantic-settings~=2.12.0
Requires-Dist: pydantic~=2.12.5
Requires-Dist: pygments-cache~=0.1.3
Requires-Dist: pyseccomp~=0.1.2; sys_platform == 'linux'
Requires-Dist: python-dotenv~=1.2.1
Requires-Dist: python-multipart~=0.0.21
Requires-Dist: pyyaml~=6.0.3
Requires-Dist: rich~=14.2.0
Requires-Dist: trafilatura~=2.0.0
Requires-Dist: types-aiofiles~=25.1.0.20251011
Requires-Dist: types-jsonschema~=4.25.1.20251009
Requires-Dist: types-pyyaml~=6.0.12.20250915
